{
  "new_count": 13,
  "new_posts": [
    {
      "category": "입시뉴스",
      "first_seen_at": "2026-05-28T02:24:09.353253+09:00",
      "last_changed_at": "2026-05-28T02:24:09.353253+09:00",
      "log_no": "224298481069",
      "post_url": "https://blog.naver.com/hongbis/224298481069",
      "published_at": "2026-05-28T00:39:29+09:00",
      "title": "고3 때 배울 과목까지 확정해야... 고교학점제 수강신청 내달 시작"
    },
    {
      "category": "시간표",
      "first_seen_at": "2026-05-28T00:27:02.541827+09:00",
      "last_changed_at": "2026-05-28T00:27:02.541827+09:00",
      "log_no": "224298446470",
      "post_url": "https://blog.naver.com/hongbis/224298446470",
      "published_at": "2026-05-27T23:49:49+09:00",
      "title": "대치퍼스트 중등기말고사 과학시간표"
    },
    {
      "category": "시간표",
      "first_seen_at": "2026-05-28T00:27:02.541827+09:00",
      "last_changed_at": "2026-05-28T00:27:02.541827+09:00",
      "log_no": "224298444099",
      "post_url": "https://blog.naver.com/hongbis/224298444099",
      "published_at": "2026-05-27T23:46:44+09:00",
      "title": "대치시대인재 고1 6월 단기특강"
    },
    {
      "category": "비교과",
      "first_seen_at": "2026-05-28T00:27:02.541827+09:00",
      "last_changed_at": "2026-05-28T00:27:02.541827+09:00",
      "log_no": "224298439674",
      "post_url": "https://blog.naver.com/hongbis/224298439674",
      "published_at": "2026-05-27T23:40:55+09:00",
      "title": "한국중학생화학대회(KMChC) 대회"
    },
    {
      "category": "시간표",
      "first_seen_at": "2026-05-27T22:34:04.232085+09:00",
      "last_changed_at": "2026-05-27T22:34:04.232085+09:00",
      "log_no": "224298317956",
      "post_url": "https://blog.naver.com/hongbis/224298317956",
      "published_at": "2026-05-27T21:13:58+09:00",
      "title": "안보라학원 26년 6월~ 26년 8월 독서리스트"
    },
    {
      "category": "설명회",
      "first_seen_at": "2026-05-27T22:34:04.232085+09:00",
      "last_changed_at": "2026-05-27T22:34:04.232085+09:00",
      "log_no": "224298316620",
      "post_url": "https://blog.naver.com/hongbis/224298316620",
      "published_at": "2026-05-27T21:12:18+09:00",
      "title": "김영준국어 2028 대학입시 시행 계획 안내 및 예비 고1(現중3) 여름방학 커리큘럼 설명회"
    },
    {
      "category": "세특자료실",
      "first_seen_at": "2026-05-27T20:27:29.597593+09:00",
      "last_changed_at": "2026-05-27T20:27:29.597593+09:00",
      "log_no": "224298275458",
      "post_url": "https://blog.naver.com/hongbis/224298275458",
      "published_at": "2026-05-27T20:20:48+09:00",
      "title": "왜 10명 중 9명은 오른손잡이일까\"…이유 밝혀졌다"
    },
    {
      "category": "선배들의공부방법모음",
      "first_seen_at": "2026-05-27T19:24:08.435134+09:00",
      "last_changed_at": "2026-05-27T19:24:08.435134+09:00",
      "log_no": "224298218345",
      "post_url": "https://blog.naver.com/hongbis/224298218345",
      "published_at": "2026-05-27T19:04:37+09:00",
      "title": "[3년 전 오늘] KAIST, 서울대 동시 합격 비결은"
    },
    {
      "category": "화장실명언",
      "first_seen_at": "2026-05-27T19:24:08.435134+09:00",
      "last_changed_at": "2026-05-27T19:24:08.435134+09:00",
      "log_no": "224298217955",
      "post_url": "https://blog.naver.com/hongbis/224298217955",
      "published_at": "2026-05-27T19:04:10+09:00",
      "title": "[3년 전 오늘] 웬수 같은 자식들, 세상 날것들의 사춘기"
    },
    {
      "category": "입시뉴스",
      "first_seen_at": "2026-05-27T19:24:08.435134+09:00",
      "last_changed_at": "2026-05-27T19:24:08.435134+09:00",
      "log_no": "224298217119",
      "post_url": "https://blog.naver.com/hongbis/224298217119",
      "published_at": "2026-05-27T19:03:02+09:00",
      "title": "과기특성화대…AI단과대 신설로 400명 늘린다"
    },
    {
      "category": "설명회",
      "first_seen_at": "2026-05-27T19:24:08.435134+09:00",
      "last_changed_at": "2026-05-27T19:24:08.435134+09:00",
      "log_no": "224298209362",
      "post_url": "https://blog.naver.com/hongbis/224298209362",
      "published_at": "2026-05-27T18:53:35+09:00",
      "title": "피오르에듀 고입 온라인 설명회 06.01"
    },
    {
      "category": "입시뉴스",
      "first_seen_at": "2026-05-27T19:24:08.435134+09:00",
      "last_changed_at": "2026-05-27T19:24:08.435134+09:00",
      "log_no": "224298206001",
      "post_url": "https://blog.naver.com/hongbis/224298206001",
      "published_at": "2026-05-27T18:49:24+09:00",
      "title": "어쩌다 그런 연구를?…‘괴짜 노벨상’ 이그노벨상 수상자 국내서 첫 대중강연"
    },
    {
      "category": "설명회",
      "first_seen_at": "2026-05-27T18:27:42.434864+09:00",
      "last_changed_at": "2026-05-27T18:27:42.434864+09:00",
      "log_no": "224298106302",
      "post_url": "https://blog.naver.com/hongbis/224298106302",
      "published_at": "2026-05-27T17:07:39+09:00",
      "title": "대치세정 한강의 흐름T 고3 6평 분석 및 입시 전략 설명회"
    }
  ],
  "updated_count": 0,
  "updated_posts": [],
  "window_end": "2026-05-28T08:00:00+09:00",
  "window_start": "2026-05-27T18:00:00+09:00"
}
