{
  "key": "2026-06-24",
  "post_count": 5,
  "posts": [
    {
      "category": "시간표",
      "first_seen_at": "2026-06-24T14:39:28.491516+09:00",
      "image_count": 2,
      "last_changed_at": "2026-06-24T14:39:28.491516+09:00",
      "link_count": 0,
      "log_no": "224325736354",
      "place_count": 0,
      "post_url": "https://blog.naver.com/hongbis/224325736354",
      "published_at": "2026-06-24T14:19:29+09:00",
      "text_length": 0,
      "title": "대치수학의힘 여름방학특강"
    },
    {
      "category": "시간표",
      "first_seen_at": "2026-06-24T14:39:28.491516+09:00",
      "image_count": 2,
      "last_changed_at": "2026-06-24T14:39:28.491516+09:00",
      "link_count": 1,
      "log_no": "224325723620",
      "place_count": 0,
      "post_url": "https://blog.naver.com/hongbis/224325723620",
      "published_at": "2026-06-24T14:08:06+09:00",
      "text_length": 760,
      "title": "다원목동 예비고1 여름방학 영어 특강"
    },
    {
      "category": "엄마공부",
      "first_seen_at": "2026-06-24T14:39:28.491516+09:00",
      "image_count": 0,
      "last_changed_at": "2026-06-24T14:39:28.491516+09:00",
      "link_count": 0,
      "log_no": "224325717048",
      "place_count": 0,
      "post_url": "https://blog.naver.com/hongbis/224325717048",
      "published_at": "2026-06-24T14:01:47+09:00",
      "text_length": 0,
      "title": "[3년 전 오늘] 아들을 공부하는 엄마들"
    },
    {
      "category": "엄마공부",
      "first_seen_at": "2026-06-24T14:39:28.491516+09:00",
      "image_count": 0,
      "last_changed_at": "2026-06-24T14:39:28.491516+09:00",
      "link_count": 0,
      "log_no": "224325716515",
      "place_count": 0,
      "post_url": "https://blog.naver.com/hongbis/224325716515",
      "published_at": "2026-06-24T14:01:16+09:00",
      "text_length": 0,
      "title": "[2년 전 오늘] 다정하게 뼈 때리는 언니들의 조언"
    },
    {
      "category": "입시뉴스",
      "first_seen_at": "2026-06-24T14:39:28.491516+09:00",
      "image_count": 1,
      "last_changed_at": "2026-06-24T14:39:28.491516+09:00",
      "link_count": 0,
      "log_no": "224325699929",
      "place_count": 0,
      "post_url": "https://blog.naver.com/hongbis/224325699929",
      "published_at": "2026-06-24T13:45:27+09:00",
      "text_length": 0,
      "title": "고교학점제 시대를 준비하는 중학생의 ‘방학 중 진로 탐색’과 ‘과목 선택 전략’"
    }
  ],
  "updated_at": "2026-06-24T14:39:28.491516+09:00"
}
