{
  "key": "2026-04-10",
  "post_count": 1,
  "posts": [
    {
      "category": "엄마공부",
      "first_seen_at": "2026-04-10T12:24:15.024967+09:00",
      "image_count": 1,
      "last_changed_at": "2026-04-10T12:24:15.024967+09:00",
      "link_count": 0,
      "log_no": "224247501261",
      "place_count": 0,
      "post_url": "https://blog.naver.com/hongbis/224247501261",
      "published_at": "2026-04-10T11:10:56+09:00",
      "text_length": 0,
      "title": "재물이 절대 모이지 않는 집에 꼭 있는 것, 눈에 띄는대로 버려라"
    }
  ],
  "updated_at": "2026-04-10T12:24:15.024967+09:00"
}
